tsroots/__init__.py
tsroots/decoupled_GP.py
tsroots/max_k_sum.py
tsroots/optim.py
tsroots/preprocessor.py
tsroots/utils.py
tsroots-0.1.22.dist-info/LICENSE
tsroots-0.1.22.dist-info/METADATA
tsroots-0.1.22.dist-info/WHEEL
tsroots-0.1.22.dist-info/top_level.txt
tsroots-0.1.22.dist-info/RECORD
