Metadata-Version: 2.2
Name: tsroots
Version: 0.1.22
Summary: Optimizing Posterior Samples for Bayesian Optimization via Rootfinding
Author-email: Taiwo Adebiyi <taadebi2@cougarnet.uh.edu>, Ruda Zhang <rudaz@uh.edu>, Bach Do <bdo3@uh.edu>
License: MIT
Project-URL: Repository, https://github.com/UQUH/TSRoots
Requires-Python: >=3.7
License-File: LICENSE
Requires-Dist: numpy
Requires-Dist: scipy
Requires-Dist: matplotlib
Requires-Dist: gpytorch
Requires-Dist: pyDOE3
Requires-Dist: joblib
Provides-Extra: pytorch
Requires-Dist: torch; extra == "pytorch"
Provides-Extra: docs
Requires-Dist: sphinx; extra == "docs"
Requires-Dist: sphinx-rtd-theme; extra == "docs"
Provides-Extra: test
Requires-Dist: pytest; extra == "test"
Requires-Dist: coverage; extra == "test"
Requires-Dist: pytest-cov; extra == "test"
